Workbook

Sheet README
A1: Ericsson Networks: margin bridge on a simulated deal portfolio
A2: Built by Anh Thy (Anna) Tran for the Early Career Program, Commercial Analytics Manager application (Req 791802).
A4: What this is
A5: A simulated portfolio of 123 deal lines sold to fictional operators across Ericsson's four market areas, in two quarters (Q2-26 and Q3-26).
A6: Each deal mixes four product lines: Radio Hardware, RAN Software, Rollout Services and Support Services.
A7: All deal data is SIMULATED. It is not Ericsson data. Prices, discounts and costs are illustrative.
A9: Question it answers
A10: Why did gross margin fall between the two quarters, and how much of the drop came from product mix, price (discount) and cost?
A12: How to read it
A13: Deals: one row per deal line. Blue cells are inputs; black cells are formulas.
A14: Margin Bridge: change the yellow period cells to compare any two quarters. The bridge splits the gross margin change into three effects:
A15: Mix effect = (share of sales in period B - share in period A) x (product line margin A - total margin A). A line that grows its share with a below-average margin pulls the total down.
... A27: Source: Ericsson Second quarter report 2026 (14 July 2026), https://www.ericsson.com/en/investors ; press coverage: RTTNews, 14 July 2026.

Sheet Deals
A1: Deal ID | B1: Quarter | C1: Market Area | D1: Customer | E1: Deal Type | F1: Product Line | G1: Unit | H1: Units | I1: List Price (SEK k/unit) | J1: Discount | K1: Unit Cost (SEK k/unit) | L1: Net Price (SEK k/unit) | M1: List Sales (SEK k) | N1: Net Sales (SEK k) | O1: COGS (SEK k) | P1: Gross Margin (SEK k) | Q1: GM %
A2: Q2-AME-01 | B2: Q2-26 | C2: Americas | D2: Operator C | E2: Network modernisation | F2: Radio Hardware | G2: radio unit | H2: 912 | I2: 95 | J2: 0.261 | K2: 33.9 | L2: =I2*(1-J2) -> 70.205 | M2: =H2*I2 -> 86640 | N2: =H2*L2 -> 64026.96 | O2: =H2*K2 -> 30916.8 | P2: =N2-O2 -> 33110.16 | Q2: =IF(N2=0,0,P2/N2) -> 0.51712841
A3: Q2-AME-01 | B3: Q2-26 | C3: Americas | D3: Operator C | E3: Network modernisation | F3: RAN Software | G3: feature licence | H3: 725 | I3: 40 | J3: 0.278 | K3: 5.7 | L3: =I3*(1-J3) -> 28.88 | M3: =H3*I3 -> 29000 | N3: =H3*L3 -> 20938 | O3: =H3*K3 -> 4132.5 | P3: =N3-O3 -> 16805.5 | Q3: =IF(N3=0,0,P3/N3) -> 0.80263158
A4: Q2-AME-01 | B4: Q2-26 | C4: Americas | D4: Operator C | E4: Network modernisation | F4: Rollout Services | G4: site | H4: 84 | I4: 180 | J4: 0.076 | K4: 142.6 | L4: =I4*(1-J4) -> 166.32 | M4: =H4*I4 -> 15120 | N4: =H4*L4 -> 13970.88 | O4: =H4*K4 -> 11978.4 | P4: =N4-O4 -> 1992.48 | Q4: =IF(N4=0,0,P4/N4) -> 0.14261664
A5: Q2-AME-01 | B5: Q2-26 | C5: Americas | D5: Operator C | E5: Network modernisation | F5: Support Services | G5: site-year | H5: 304 | I5: 66 | J5: 0.088 | K5: 32.5 | L5: =I5*(1-J5) -> 60.192 | M5: =H5*I5 -> 20064 | N5: =H5*L5 -> 18298.368 | O5: =H5*K5 -> 9880 | P5: =N5-O5 -> 8418.368 | Q5: =IF(N5=0,0,P5/N5) -> 0.46006114
A6: Q2-AME-02 | B6: Q2-26 | C6: Americas | D6: Operator B | E6: New site rollout | F6: Radio Hardware | G6: radio unit | H6: 492 | I6: 95 | J6: 0.293 | K6: 32.6 | L6: =I6*(1-J6) -> 67.165 | M6: =H6*I6 -> 46740 | N6: =H6*L6 -> 33045.18 | O6: =H6*K6 -> 16039.2 | P6: =N6-O6 -> 17005.98 | Q6: =IF(N6=0,0,P6/N6) -> 0.51462815
A7: Q2-AME-02 | B7: Q2-26 | C7: Americas | D7: Operator B | E7: New site rollout | F7: RAN Software | G7: feature licence | H7: 418 | I7: 40 | J7: 0.319 | K7: 5.5 | L7: =I7*(1-J7) -> 27.24 | M7: =H7*I7 -> 16720 | N7: =H7*L7 -> 11386.32 | O7: =H7*K7 -> 2299 | P7: =N7-O7 -> 9087.32 | Q7: =IF(N7=0,0,P7/N7) -> 0.79809104
A8: Q2-AME-02 | B8: Q2-26 | C8: Americas | D8: Operator B | E8: New site rollout | F8: Rollout Services | G8: site | H8: 92 | I8: 180 | J8: 0.064 | K8: 143.3 | L8: =I8*(1-J8) -> 168.48 | M8: =H8*I8 -> 16560 | N8: =H8*L8 -> 15500.16 | O8: =H8*K8 -> 13183.6 | P8: =N8-O8 -> 2316.56 | Q8: =IF(N8=0,0,P8/N8) -> 0.14945394
A9: Q2-AME-02 | B9: Q2-26 | C9: Americas | D9: Operator B | E9: New site rollout | F9: Support Services | G9: site-year | H9: 164 | I9: 66 | J9: 0.106 | K9: 32.9 | L9: =I9*(1-J9) -> 59.004 | M9: =H9*I9 -> 10824 | N9: =H9*L9 -> 9676.656 | O9: =H9*K9 -> 5395.6 | P9: =N9-O9 -> 4281.056 | Q9: =IF(N9=0,0,P9/N9) -> 0.44241068
A10: Q2-AME-03 | B10: Q2-26 | C10: Americas | D10: Operator B | E10: New site rollout | F10: Radio Hardware | G10: radio unit | H10: 705 | I10: 95 | J10: 0.278 | K10: 33.6 | L10: =I10*(1-J10) -> 68.59 | M10: =H10*I10 -> 66975 | N10: =H10*L10 -> 48355.95 | O10: =H10*K10 -> 23688 | P10: =N10-O10 -> 24667.95 | Q10: =IF(N10=0,0,P10/N10) -> 0.51013267
A11: Q2-AME-03 | B11: Q2-26 | C11: Americas | D11: Operator B | E11: New site rollout | F11: RAN Software | G11: feature licence | H11: 593 | I11: 40 | J11: 0.286 | K11: 5.7 | L11: =I11*(1-J11) -> 28.56 | M11: =H11*I11 -> 23720 | N11: =H11*L11 -> 16936.08 | O11: =H11*K11 -> 3380.1 | P11: =N11-O11 -> 13555.98 | Q11: =IF(N11=0,0,P11/N11) -> 0.80042017
A12: Q2-AME-03 | B12: Q2-26 | C12: Americas | D12: Operator B | E12: New site rollout | F12: Rollout Services | G12: site | H12: 134 | I12: 180 | J12: 0.056 | K12: 140.5 | L12: =I12*(1-J12) -> 169.92 | M12: =H12*I12 -> 24120 | N12: =H12*L12 -> 22769.28 | O12: =H12*K12 -> 18827 | P12: =N12-O12 -> 3942.28 | Q12: =IF(N12=0,0,P12/N12) -> 0.1731403
A13: Q2-AME-03 | B13: Q2-26 | C13: Americas | D13: Operator B | E13: New site rollout | F13: Support Services | G13: site-year | H13: 235 | I13: 66 | J13: 0.128 | K13: 32.5 | L13: =I13*(1-J13) -> 57.552 | M13: =H13*I13 -> 15510 | N13: =H13*L13 -> 13524.72 | O13: =H13*K13 -> 7637.5 | P13: =N13-O13 -> 5887.22 | Q13: =IF(N13=0,0,P13/N13) -> 0.4352933
... A124: Q3-SOU-05 | B124: Q3-26 | C124: South East Asia, Oceania & India | D124: Operator K | E124: New site rollout | F124: Support Services | G124: site-year | H124: 300 | I124: 66 | J124: 0.097 | K124: 32.8 | L124: =I124*(1-J124) -> 59.598 | M124: =H124*I124 -> 19800 | N124: =H124*L124 -> 17879.4 | O124: =H124*K124 -> 9840 | P124: =N124-O124 -> 8039.4 | Q124: =IF(N124=0,0,P124/N124) -> 0.44964596

Sheet Margin Bridge
A1: Gross margin bridge: what moved between two quarters
A2: Simulated deal data. Change the yellow cells to compare other periods.
A4: Period A | B4: Q2-26 | D4: Metric | E4: =B4 -> Q2-26 | F4: =B5 -> Q3-26 | G4: Change
A5: Period B | B5: Q3-26 | D5: Net sales (SEK m) | E5: =SUMIFS(Deals!$N$2:$N$124,Deals!$B$2:$B$124,$B$4)/1000 -> 1475.009 | F5: =SUMIFS(Deals!$N$2:$N$124,Deals!$B$2:$B$124,$B$5)/1000 -> 1779.5087 | G5: =IF(E5=0,0,F5/E5-1) -> 0.2064392
D6: Gross margin (SEK m) | E6: =SUMIFS(Deals!$P$2:$P$124,Deals!$B$2:$B$124,$B$4)/1000 -> 749.82942 | F6: =SUMIFS(Deals!$P$2:$P$124,Deals!$B$2:$B$124,$B$5)/1000 -> 862.0929 | G6: =IF(E6=0,0,F6/E6-1) -> 0.14971869
D7: Gross margin % | E7: =IF(E5=0,0,E6/E5) -> 0.50835582 | F7: =IF(F5=0,0,F6/F5) -> 0.48445557 | G7: =F7-E7 -> -0.023900251 | H7: (percentage points)
A10: Product Line | B10: Units A | C10: Net Sales A (SEK k) | D10: COGS A (SEK k) | E10: Units B | F10: Net Sales B (SEK k) | G10: COGS B (SEK k) | H10: Share of sales A | I10: Share of sales B | J10: GM % A | K10: GM % B | L10: Net price A (SEK k/unit) | M10: Net price B (SEK k/unit) | N10: Unit cost A (SEK k/unit) | O10: Unit cost B (SEK k/unit) | P10: Mix effect (pp) | Q10: Price effect (pp) | R10: Cost effect (pp) | S10: Total (pp)
A11: Radio Hardware | B11: =SUMIFS(Deals!$H$2:$H$124,Deals!$F$2:$F$124,$A11,Deals!$B$2:$B$124,$B$4) -> 11520 | C11: =SUMIFS(Deals!$N$2:$N$124,Deals!$F$2:$F$124,$A11,Deals!$B$2:$B$124,$B$4) -> 782338.68 | D11: =SUMIFS(Deals!$O$2:$O$124,Deals!$F$2:$F$124,$A11,Deals!$B$2:$B$124,$B$4) -> 383812.8 | E11: =SUMIFS(Deals!$H$2:$H$124,Deals!$F$2:$F$124,$A11,Deals!$B$2:$B$124,$B$5) -> 13728 | F11: =SUMIFS(Deals!$N$2:$N$124,Deals!$F$2:$F$124,$A11,Deals!$B$2:$B$124,$B$5) -> 921064.43 | G11: =SUMIFS(Deals!$O$2:$O$124,Deals!$F$2:$F$124,$A11,Deals!$B$2:$B$124,$B$5) -> 469882.2 | H11: =IF($C$15=0,0,C11/$C$15) -> 0.53039586 | I11: =IF($F$15=0,0,F11/$F$15) -> 0.51759479 | J11: =IF(C11=0,0,1-D11/C11) -> 0.50940327 | K11: =IF(F11=0,0,1-G11/F11) -> 0.48984871 | L11: =IF(B11=0,0,C11/B11) -> 67.911344 | M11: =IF(E11=0,0,F11/E11) -> 67.093854 | N11: =IF(B11=0,0,D11/B11) -> 33.317083 | O11: =IF(E11=0,0,G11/E11) -> 34.228016 | P11: =(I11-H11)*(J11-$J$15) -> -1.3408438e-05 | Q11: =IF(M11=0,0,I11*((1-N11/M11)-J11)) -> -0.0030939567 | R11: =IF(M11=0,0,I11*(K11-(1-N11/M11))) -> -0.0070273778 | S11: =P11+Q11+R11 -> -0.010134743
A12: RAN Software | B12: =SUMIFS(Deals!$H$2:$H$124,Deals!$F$2:$F$124,$A12,Deals!$B$2:$B$124,$B$4) -> 9765 | C12: =SUMIFS(Deals!$N$2:$N$124,Deals!$F$2:$F$124,$A12,Deals!$B$2:$B$124,$B$4) -> 274321.04 | D12: =SUMIFS(Deals!$O$2:$O$124,Deals!$F$2:$F$124,$A12,Deals!$B$2:$B$124,$B$4) -> 54726.1 | E12: =SUMIFS(Deals!$H$2:$H$124,Deals!$F$2:$F$124,$A12,Deals!$B$2:$B$124,$B$5) -> 11455 | F12: =SUMIFS(Deals!$N$2:$N$124,Deals!$F$2:$F$124,$A12,Deals!$B$2:$B$124,$B$5) -> 312542 | G12: =SUMIFS(Deals!$O$2:$O$124,Deals!$F$2:$F$124,$A12,Deals!$B$2:$B$124,$B$5) -> 64034.1 | H12: =IF($C$15=0,0,C12/$C$15) -> 0.18597923 | I12: =IF($F$15=0,0,F12/$F$15) -> 0.17563387 | J12: =IF(C12=0,0,1-D12/C12) -> 0.80050345 | K12: =IF(F12=0,0,1-G12/F12) -> 0.79511842 | L12: =IF(B12=0,0,C12/B12) -> 28.092272 | M12: =IF(E12=0,0,F12/E12) -> 27.28433 | N12: =IF(B12=0,0,D12/B12) -> 5.6043113 | O12: =IF(E12=0,0,G12/E12) -> 5.5900567 | P12: =(I12-H12)*(J12-$J$15) -> -0.003022372 | Q12: =IF(M12=0,0,I12*((1-N12/M12)-J12)) -> -0.0010375541 | R12: =IF(M12=0,0,I12*(K12-(1-N12/M12))) -> 9.1759104e-05 | S12: =P12+Q12+R12 -> -0.003968167
A13: Rollout Services | B13: =SUMIFS(Deals!$H$2:$H$124,Deals!$F$2:$F$124,$A13,Deals!$B$2:$B$124,$B$4) -> 1155 | C13: =SUMIFS(Deals!$N$2:$N$124,Deals!$F$2:$F$124,$A13,Deals!$B$2:$B$124,$B$4) -> 191297.16 | D13: =SUMIFS(Deals!$O$2:$O$124,Deals!$F$2:$F$124,$A13,Deals!$B$2:$B$124,$B$4) -> 161409.7 | E13: =SUMIFS(Deals!$H$2:$H$124,Deals!$F$2:$F$124,$A13,Deals!$B$2:$B$124,$B$5) -> 1670 | F13: =SUMIFS(Deals!$N$2:$N$124,Deals!$F$2:$F$124,$A13,Deals!$B$2:$B$124,$B$5) -> 273157.74 | G13: =SUMIFS(Deals!$O$2:$O$124,Deals!$F$2:$F$124,$A13,Deals!$B$2:$B$124,$B$5) -> 234066.3 | H13: =IF($C$15=0,0,C13/$C$15) -> 0.1296922 | I13: =IF($F$15=0,0,F13/$F$15) -> 0.15350177 | J13: =IF(C13=0,0,1-D13/C13) -> 0.15623577 | K13: =IF(F13=0,0,1-G13/F13) -> 0.1431094 | L13: =IF(B13=0,0,C13/B13) -> 165.62525 | M13: =IF(E13=0,0,F13/E13) -> 163.56751 | N13: =IF(B13=0,0,D13/B13) -> 139.74866 | O13: =IF(E13=0,0,G13/E13) -> 140.15946 | P13: =(I13-H13)*(J13-$J$15) -> -0.008383829 | Q13: =IF(M13=0,0,I13*((1-N13/M13)-J13)) -> -0.0016293992 | R13: =IF(M13=0,0,I13*(K13-(1-N13/M13))) -> -0.00038552277 | S13: =P13+Q13+R13 -> -0.010398751
A14: Support Services | B14: =SUMIFS(Deals!$H$2:$H$124,Deals!$F$2:$F$124,$A14,Deals!$B$2:$B$124,$B$4) -> 3840 | C14: =SUMIFS(Deals!$N$2:$N$124,Deals!$F$2:$F$124,$A14,Deals!$B$2:$B$124,$B$4) -> 227052.14 | D14: =SUMIFS(Deals!$O$2:$O$124,Deals!$F$2:$F$124,$A14,Deals!$B$2:$B$124,$B$4) -> 125231 | E14: =SUMIFS(Deals!$H$2:$H$124,Deals!$F$2:$F$124,$A14,Deals!$B$2:$B$124,$B$5) -> 4576 | F14: =SUMIFS(Deals!$N$2:$N$124,Deals!$F$2:$F$124,$A14,Deals!$B$2:$B$124,$B$5) -> 272744.54 | G14: =SUMIFS(Deals!$O$2:$O$124,Deals!$F$2:$F$124,$A14,Deals!$B$2:$B$124,$B$5) -> 149433.2 | H14: =IF($C$15=0,0,C14/$C$15) -> 0.15393272 | I14: =IF($F$15=0,0,F14/$F$15) -> 0.15326957 | J14: =IF(C14=0,0,1-D14/C14) -> 0.44844828 | K14: =IF(F14=0,0,1-G14/F14) -> 0.45211295 | L14: =IF(B14=0,0,C14/B14) -> 59.128163 | M14: =IF(E14=0,0,F14/E14) -> 59.603264 | N14: =IF(B14=0,0,D14/B14) -> 32.61224 | O14: =IF(E14=0,0,G14/E14) -> 32.655857 | P14: =(I14-H14)*(J14-$J$15) -> 3.9727252e-05 | Q14: =IF(M14=0,0,I14*((1-N14/M14)-J14)) -> 0.00067384332 | R14: =IF(M14=0,0,I14*(K14-(1-N14/M14))) -> -0.00011216111 | S14: =P14+Q14+R14 -> 0.00060140947
A15: Total | B15: =SUM(B11:B14) -> 26280 | C15: =SUM(C11:C14) -> 1475009 | D15: =SUM(D11:D14) -> 725179.6 | E15: =SUM(E11:E14) -> 31429 | F15: =SUM(F11:F14) -> 1779508.7 | G15: =SUM(G11:G14) -> 917415.8 | H15: =SUM(H11:H14) -> 1 | I15: =SUM(I11:I14) -> 1 | J15: =IF(C15=0,0,1-D15/C15) -> 0.50835582 | K15: =IF(F15=0,0,1-G15/F15) -> 0.48445557 | P15: =SUM(P11:P14) -> -0.011379882 | Q15: =SUM(Q11:Q14) -> -0.0050870667 | R15: =SUM(R11:R14) -> -0.0074333026 | S15: =SUM(S11:S14) -> -0.023900251
A17: Check: effects sum to the total margin change | F17: =S15-(K15-J15) -> 0 | G17: =IF(ABS(F17)<0.000001,"OK","Check") -> OK
A20: Waterfall helper (feeds the chart)
A21: Step | B21: Value | C21: Cumulative | D21: Base | E21: Decrease | F21: Increase | G21: Total
A22: =$B$4&" gross margin" -> Q2-26 gross margin | B22: =J15 -> 0.50835582 | C22: =B22 -> 0.50835582 | D22: 0 | E22: 0 | F22: 0 | G22: =B22 -> 0.50835582
A23: Mix | B23: =P15 -> -0.011379882 | C23: =C22+B23 -> 0.49697594 | D23: =MIN(C22,C23) -> 0.49697594 | E23: =MAX(0,C22-C23) -> 0.011379882 | F23: =MAX(0,C23-C22) -> 0 | G23: 0
A24: Price / discount | B24: =Q15 -> -0.0050870667 | C24: =C23+B24 -> 0.49188887 | D24: =MIN(C23,C24) -> 0.49188887 | E24: =MAX(0,C23-C24) -> 0.0050870667 | F24: =MAX(0,C24-C23) -> 0 | G24: 0
A25: Cost | B25: =R15 -> -0.0074333026 | C25: =C24+B25 -> 0.48445557 | D25: =MIN(C24,C25) -> 0.48445557 | E25: =MAX(0,C24-C25) -> 0.0074333026 | F25: =MAX(0,C25-C24) -> 0 | G25: 0
A26: =$B$5&" gross margin" -> Q3-26 gross margin | B26: =K15 -> 0.48445557 | C26: =B26 -> 0.48445557 | D26: 0 | E26: 0 | F26: 0 | G26: =B26 -> 0.48445557

Sheet Discounts
A1: Average discount off list price, by market area and product line
A2: Periods follow the yellow cells on 'Margin Bridge'. Red = discount deepened by 2pp or more.
A4: Market Area | B4: Product Line | C4: List sales A (SEK k) | D4: Net sales A (SEK k) | E4: Avg discount A | F4: List sales B (SEK k) | G4: Net sales B (SEK k) | H4: Avg discount B | I4: Change (pp)
A5: Americas | B5: Radio Hardware | C5: =SUMIFS(Deals!$M$2:$M$124,Deals!$C$2:$C$124,$A5,Deals!$F$2:$F$124,$B5,Deals!$B$2:$B$124,'Margin Bridge'!$B$4) -> 259635 | D5: =SUMIFS(Deals!$N$2:$N$124,Deals!$C$2:$C$124,$A5,Deals!$F$2:$F$124,$B5,Deals!$B$2:$B$124,'Margin Bridge'!$B$4) -> 187635.45 | E5: =IF(C5=0,0,1-D5/C5) -> 0.27731065 | F5: =SUMIFS(Deals!$M$2:$M$124,Deals!$C$2:$C$124,$A5,Deals!$F$2:$F$124,$B5,Deals!$B$2:$B$124,'Margin Bridge'!$B$5) -> 261345 | G5: =SUMIFS(Deals!$N$2:$N$124,Deals!$C$2:$C$124,$A5,Deals!$F$2:$F$124,$B5,Deals!$B$2:$B$124,'Margin Bridge'!$B$5) -> 186071.08 | H5: =IF(F5=0,0,1-G5/F5) -> 0.28802508 | I5: =IF(OR(C5=0,F5=0),0,H5-E5) -> 0.010714434
A6: Americas | B6: RAN Software | C6: =SUMIFS(Deals!$M$2:$M$124,Deals!$C$2:$C$124,$A6,Deals!$F$2:$F$124,$B6,Deals!$B$2:$B$124,'Margin Bridge'!$B$4) -> 89480 | D6: =SUMIFS(Deals!$N$2:$N$124,Deals!$C$2:$C$124,$A6,Deals!$F$2:$F$124,$B6,Deals!$B$2:$B$124,'Margin Bridge'!$B$4) -> 63589 | E6: =IF(C6=0,0,1-D6/C6) -> 0.28934958 | F6: =SUMIFS(Deals!$M$2:$M$124,Deals!$C$2:$C$124,$A6,Deals!$F$2:$F$124,$B6,Deals!$B$2:$B$124,'Margin Bridge'!$B$5) -> 90880 | G6: =SUMIFS(Deals!$N$2:$N$124,Deals!$C$2:$C$124,$A6,Deals!$F$2:$F$124,$B6,Deals!$B$2:$B$124,'Margin Bridge'!$B$5) -> 63672.44 | H6: =IF(F6=0,0,1-G6/F6) -> 0.29937896 | I6: =IF(OR(C6=0,F6=0),0,H6-E6) -> 0.010029386
A7: Americas | B7: Rollout Services | C7: =SUMIFS(Deals!$M$2:$M$124,Deals!$C$2:$C$124,$A7,Deals!$F$2:$F$124,$B7,Deals!$B$2:$B$124,'Margin Bridge'!$B$4) -> 70920 | D7: =SUMIFS(Deals!$N$2:$N$124,Deals!$C$2:$C$124,$A7,Deals!$F$2:$F$124,$B7,Deals!$B$2:$B$124,'Margin Bridge'!$B$4) -> 66044.88 | E7: =IF(C7=0,0,1-D7/C7) -> 0.068741117 | F7: =SUMIFS(Deals!$M$2:$M$124,Deals!$C$2:$C$124,$A7,Deals!$F$2:$F$124,$B7,Deals!$B$2:$B$124,'Margin Bridge'!$B$5) -> 34020 | G7: =SUMIFS(Deals!$N$2:$N$124,Deals!$C$2:$C$124,$A7,Deals!$F$2:$F$124,$B7,Deals!$B$2:$B$124,'Margin Bridge'!$B$5) -> 30499.56 | H7: =IF(F7=0,0,1-G7/F7) -> 0.10348148 | I7: =IF(OR(C7=0,F7=0),0,H7-E7) -> 0.034740365
A8: Americas | B8: Support Services | C8: =SUMIFS(Deals!$M$2:$M$124,Deals!$C$2:$C$124,$A8,Deals!$F$2:$F$124,$B8,Deals!$B$2:$B$124,'Margin Bridge'!$B$4) -> 60126 | D8: =SUMIFS(Deals!$N$2:$N$124,Deals!$C$2:$C$124,$A8,Deals!$F$2:$F$124,$B8,Deals!$B$2:$B$124,'Margin Bridge'!$B$4) -> 54156.96 | E8: =IF(C8=0,0,1-D8/C8) -> 0.099275521 | F8: =SUMIFS(Deals!$M$2:$M$124,Deals!$C$2:$C$124,$A8,Deals!$F$2:$F$124,$B8,Deals!$B$2:$B$124,'Margin Bridge'!$B$5) -> 60522 | G8: =SUMIFS(Deals!$N$2:$N$124,Deals!$C$2:$C$124,$A8,Deals!$F$2:$F$124,$B8,Deals!$B$2:$B$124,'Margin Bridge'!$B$5) -> 54747 | H8: =IF(F8=0,0,1-G8/F8) -> 0.095419847 | I8: =IF(OR(C8=0,F8=0),0,H8-E8) -> -0.0038556741
A9: Europe, Middle East & Africa | B9: Radio Hardware | C9: =SUMIFS(Deals!$M$2:$M$124,Deals!$C$2:$C$124,$A9,Deals!$F$2:$F$124,$B9,Deals!$B$2:$B$124,'Margin Bridge'!$B$4) -> 315780 | D9: =SUMIFS(Deals!$N$2:$N$124,Deals!$C$2:$C$124,$A9,Deals!$F$2:$F$124,$B9,Deals!$B$2:$B$124,'Margin Bridge'!$B$4) -> 223697.92 | E9: =IF(C9=0,0,1-D9/C9) -> 0.29160199 | F9: =SUMIFS(Deals!$M$2:$M$124,Deals!$C$2:$C$124,$A9,Deals!$F$2:$F$124,$B9,Deals!$B$2:$B$124,'Margin Bridge'!$B$5) -> 306090 | G9: =SUMIFS(Deals!$N$2:$N$124,Deals!$C$2:$C$124,$A9,Deals!$F$2:$F$124,$B9,Deals!$B$2:$B$124,'Margin Bridge'!$B$5) -> 222240.15 | H9: =IF(F9=0,0,1-G9/F9) -> 0.27393855 | I9: =IF(OR(C9=0,F9=0),0,H9-E9) -> -0.017663438
A10: Europe, Middle East & Africa | B10: RAN Software | C10: =SUMIFS(Deals!$M$2:$M$124,Deals!$C$2:$C$124,$A10,Deals!$F$2:$F$124,$B10,Deals!$B$2:$B$124,'Margin Bridge'!$B$4) -> 113080 | D10: =SUMIFS(Deals!$N$2:$N$124,Deals!$C$2:$C$124,$A10,Deals!$F$2:$F$124,$B10,Deals!$B$2:$B$124,'Margin Bridge'!$B$4) -> 80410.8 | E10: =IF(C10=0,0,1-D10/C10) -> 0.28890343 | F10: =SUMIFS(Deals!$M$2:$M$124,Deals!$C$2:$C$124,$A10,Deals!$F$2:$F$124,$B10,Deals!$B$2:$B$124,'Margin Bridge'!$B$5) -> 101000 | G10: =SUMIFS(Deals!$N$2:$N$124,Deals!$C$2:$C$124,$A10,Deals!$F$2:$F$124,$B10,Deals!$B$2:$B$124,'Margin Bridge'!$B$5) -> 67099.2 | H10: =IF(F10=0,0,1-G10/F10) -> 0.33565149 | I10: =IF(OR(C10=0,F10=0),0,H10-E10) -> 0.046748054
A11: Europe, Middle East & Africa | B11: Rollout Services | C11: =SUMIFS(Deals!$M$2:$M$124,Deals!$C$2:$C$124,$A11,Deals!$F$2:$F$124,$B11,Deals!$B$2:$B$124,'Margin Bridge'!$B$4) -> 41400 | D11: =SUMIFS(Deals!$N$2:$N$124,Deals!$C$2:$C$124,$A11,Deals!$F$2:$F$124,$B11,Deals!$B$2:$B$124,'Margin Bridge'!$B$4) -> 37769.76 | E11: =IF(C11=0,0,1-D11/C11) -> 0.087686957 | F11: =SUMIFS(Deals!$M$2:$M$124,Deals!$C$2:$C$124,$A11,Deals!$F$2:$F$124,$B11,Deals!$B$2:$B$124,'Margin Bridge'!$B$5) -> 65340 | G11: =SUMIFS(Deals!$N$2:$N$124,Deals!$C$2:$C$124,$A11,Deals!$F$2:$F$124,$B11,Deals!$B$2:$B$124,'Margin Bridge'!$B$5) -> 59127.48 | H11: =IF(F11=0,0,1-G11/F11) -> 0.09507989 | I11: =IF(OR(C11=0,F11=0),0,H11-E11) -> 0.0073929333
A12: Europe, Middle East & Africa | B12: Support Services | C12: =SUMIFS(Deals!$M$2:$M$124,Deals!$C$2:$C$124,$A12,Deals!$F$2:$F$124,$B12,Deals!$B$2:$B$124,'Margin Bridge'!$B$4) -> 73128 | D12: =SUMIFS(Deals!$N$2:$N$124,Deals!$C$2:$C$124,$A12,Deals!$F$2:$F$124,$B12,Deals!$B$2:$B$124,'Margin Bridge'!$B$4) -> 65548.032 | E12: =IF(C12=0,0,1-D12/C12) -> 0.10365343 | F12: =SUMIFS(Deals!$M$2:$M$124,Deals!$C$2:$C$124,$A12,Deals!$F$2:$F$124,$B12,Deals!$B$2:$B$124,'Margin Bridge'!$B$5) -> 70884 | G12: =SUMIFS(Deals!$N$2:$N$124,Deals!$C$2:$C$124,$A12,Deals!$F$2:$F$124,$B12,Deals!$B$2:$B$124,'Margin Bridge'!$B$5) -> 64304.658 | H12: =IF(F12=0,0,1-G12/F12) -> 0.092818436 | I12: =IF(OR(C12=0,F12=0),0,H12-E12) -> -0.010834994
A13: North East Asia | B13: Radio Hardware | C13: =SUMIFS(Deals!$M$2:$M$124,Deals!$C$2:$C$124,$A13,Deals!$F$2:$F$124,$B13,Deals!$B$2:$B$124,'Margin Bridge'!$B$4) -> 268755 | D13: =SUMIFS(Deals!$N$2:$N$124,Deals!$C$2:$C$124,$A13,Deals!$F$2:$F$124,$B13,Deals!$B$2:$B$124,'Margin Bridge'!$B$4) -> 189690.3 | E13: =IF(C13=0,0,1-D13/C13) -> 0.29418876 | F13: =SUMIFS(Deals!$M$2:$M$124,Deals!$C$2:$C$124,$A13,Deals!$F$2:$F$124,$B13,Deals!$B$2:$B$124,'Margin Bridge'!$B$5) -> 297825 | G13: =SUMIFS(Deals!$N$2:$N$124,Deals!$C$2:$C$124,$A13,Deals!$F$2:$F$124,$B13,Deals!$B$2:$B$124,'Margin Bridge'!$B$5) -> 213402.58 | H13: =IF(F13=0,0,1-G13/F13) -> 0.28346316 | I13: =IF(OR(C13=0,F13=0),0,H13-E13) -> -0.010725601
A14: North East Asia | B14: RAN Software | C14: =SUMIFS(Deals!$M$2:$M$124,Deals!$C$2:$C$124,$A14,Deals!$F$2:$F$124,$B14,Deals!$B$2:$B$124,'Margin Bridge'!$B$4) -> 95960 | D14: =SUMIFS(Deals!$N$2:$N$124,Deals!$C$2:$C$124,$A14,Deals!$F$2:$F$124,$B14,Deals!$B$2:$B$124,'Margin Bridge'!$B$4) -> 66441.12 | E14: =IF(C14=0,0,1-D14/C14) -> 0.30761651 | F14: =SUMIFS(Deals!$M$2:$M$124,Deals!$C$2:$C$124,$A14,Deals!$F$2:$F$124,$B14,Deals!$B$2:$B$124,'Margin Bridge'!$B$5) -> 103840 | G14: =SUMIFS(Deals!$N$2:$N$124,Deals!$C$2:$C$124,$A14,Deals!$F$2:$F$124,$B14,Deals!$B$2:$B$124,'Margin Bridge'!$B$5) -> 71615.96 | H14: =IF(F14=0,0,1-G14/F14) -> 0.31032396 | I14: =IF(OR(C14=0,F14=0),0,H14-E14) -> 0.0027074531
A15: North East Asia | B15: Rollout Services | C15: =SUMIFS(Deals!$M$2:$M$124,Deals!$C$2:$C$124,$A15,Deals!$F$2:$F$124,$B15,Deals!$B$2:$B$124,'Margin Bridge'!$B$4) -> 30420 | D15: =SUMIFS(Deals!$N$2:$N$124,Deals!$C$2:$C$124,$A15,Deals!$F$2:$F$124,$B15,Deals!$B$2:$B$124,'Margin Bridge'!$B$4) -> 28013.04 | E15: =IF(C15=0,0,1-D15/C15) -> 0.07912426 | F15: =SUMIFS(Deals!$M$2:$M$124,Deals!$C$2:$C$124,$A15,Deals!$F$2:$F$124,$B15,Deals!$B$2:$B$124,'Margin Bridge'!$B$5) -> 38880 | G15: =SUMIFS(Deals!$N$2:$N$124,Deals!$C$2:$C$124,$A15,Deals!$F$2:$F$124,$B15,Deals!$B$2:$B$124,'Margin Bridge'!$B$5) -> 35819.28 | H15: =IF(F15=0,0,1-G15/F15) -> 0.078722222 | I15: =IF(OR(C15=0,F15=0),0,H15-E15) -> -0.00040203813
A16: North East Asia | B16: Support Services | C16: =SUMIFS(Deals!$M$2:$M$124,Deals!$C$2:$C$124,$A16,Deals!$F$2:$F$124,$B16,Deals!$B$2:$B$124,'Margin Bridge'!$B$4) -> 62238 | D16: =SUMIFS(Deals!$N$2:$N$124,Deals!$C$2:$C$124,$A16,Deals!$F$2:$F$124,$B16,Deals!$B$2:$B$124,'Margin Bridge'!$B$4) -> 55846.494 | E16: =IF(C16=0,0,1-D16/C16) -> 0.10269459 | F16: =SUMIFS(Deals!$M$2:$M$124,Deals!$C$2:$C$124,$A16,Deals!$F$2:$F$124,$B16,Deals!$B$2:$B$124,'Margin Bridge'!$B$5) -> 68970 | G16: =SUMIFS(Deals!$N$2:$N$124,Deals!$C$2:$C$124,$A16,Deals!$F$2:$F$124,$B16,Deals!$B$2:$B$124,'Margin Bridge'!$B$5) -> 61227.936 | H16: =IF(F16=0,0,1-G16/F16) -> 0.11225263 | I16: =IF(OR(C16=0,F16=0),0,H16-E16) -> 0.0095580399
... A20: South East Asia, Oceania & India | B20: Support Services | C20: =SUMIFS(Deals!$M$2:$M$124,Deals!$C$2:$C$124,$A20,Deals!$F$2:$F$124,$B20,Deals!$B$2:$B$124,'Margin Bridge'!$B$4) -> 57948 | D20: =SUMIFS(Deals!$N$2:$N$124,Deals!$C$2:$C$124,$A20,Deals!$F$2:$F$124,$B20,Deals!$B$2:$B$124,'Margin Bridge'!$B$4) -> 51500.658 | E20: =IF(C20=0,0,1-D20/C20) -> 0.11126082 | F20: =SUMIFS(Deals!$M$2:$M$124,Deals!$C$2:$C$124,$A20,Deals!$F$2:$F$124,$B20,Deals!$B$2:$B$124,'Margin Bridge'!$B$5) -> 101640 | G20: =SUMIFS(Deals!$N$2:$N$124,Deals!$C$2:$C$124,$A20,Deals!$F$2:$F$124,$B20,Deals!$B$2:$B$124,'Margin Bridge'!$B$5) -> 92464.944 | H20: =IF(F20=0,0,1-G20/F20) -> 0.09027013 | I20: =IF(OR(C20=0,F20=0),0,H20-E20) -> -0.02099069
